[
  {
    "metadataOutputVersion" : "3.0",
    "outputSchema" : [
      {
        "hasShapeFlexibility" : "0",
        "isOptional" : "0",
        "dataType" : "Float32",
        "formattedType" : "MultiArray (Float32)",
        "shortDescription" : "",
        "shape" : "[]",
        "name" : "var_5",
        "type" : "MultiArray"
      }
    ],
    "modelParameters" : [

    ],
    "specificationVersion" : 6,
    "mlProgramOperationTypeHistogram" : {
      "RealDiv" : 1,
      "Mul" : 4,
      "ReduceSum" : 3,
      "Cast" : 3,
      "Sqrt" : 1,
      "Maximum" : 1
    },
    "computePrecision" : "Mixed (Float16, Float32, Int32)",
    "isUpdatable" : "0",
    "stateSchema" : [

    ],
    "availability" : {
      "macOS" : "12.0",
      "tvOS" : "15.0",
      "visionOS" : "1.0",
      "watchOS" : "8.0",
      "iOS" : "15.0",
      "macCatalyst" : "15.0"
    },
    "modelType" : {
      "name" : "MLModelType_mlProgram"
    },
    "userDefinedMetadata" : {
      "com.github.apple.coremltools.source_dialect" : "TorchScript",
      "com.github.apple.coremltools.source" : "torch==2.4.0",
      "com.github.apple.coremltools.version" : "8.2"
    },
    "inputSchema" : [
      {
        "hasShapeFlexibility" : "0",
        "isOptional" : "0",
        "dataType" : "Float32",
        "formattedType" : "MultiArray (Float32 1 × 384)",
        "shortDescription" : "",
        "shape" : "[1, 384]",
        "name" : "input1",
        "type" : "MultiArray"
      },
      {
        "dataType" : "Float32",
        "hasShapeFlexibility" : "1",
        "isOptional" : "0",
        "shapeFlexibility" : "1...1048576 × 384",
        "shapeRange" : "[[1, 1048576], [384, 384]]",
        "formattedType" : "MultiArray (Float32 1 × 384)",
        "type" : "MultiArray",
        "shape" : "[1, 384]",
        "name" : "input2",
        "shortDescription" : ""
      }
    ],
    "generatedClassName" : "CosineSimilarityBatched",
    "method" : "predict"
  }
]